Metadata-Version: 2.1
Name: fedj-webfinger
Version: 0.0.3
Project-URL: Homepage, https://github.com/jakekara/fedjangiverse/
Project-URL: Issues, https://github.com/jakekara/fedjangiverse/issues
Requires-Dist: django>=4
